US_statemap.py
US_statemap-0.0.1.dist-info/METADATA
US_statemap-0.0.1.dist-info/WHEEL
US_statemap-0.0.1.dist-info/entry_points.txt
US_statemap-0.0.1.dist-info/top_level.txt
US_statemap-0.0.1.dist-info/RECORD
